{"cameraMode":{"drawMode":0,"name":"Shaded","section":"Shading Mode"},"sceneLighting":false,"audioPlay":false,"sceneViewState":{"m_AlwaysRefresh":false,"showFog":true,"showSkybox":false,"showFlares":true,"showImageEffects":true,"showParticleSystems":true,"showVisualEffectGraphs":true,"m_FxEnabled":true},"in2DMode":false,"pivot":{"x":1.5786678791046143,"y":-0.5347321033477783,"z":9.408780097961426},"rotation":{"x":-0.2915911376476288,"y":-0.48537206649780276,"z":0.1757485270500183,"w":-0.8053236603736877},"size":1.6230080127716065,"orthographic":false}